semverish/__init__.py
semverish/_semverish.py
semverish/libpyversions.so
semverish-1.0.0.dist-info/METADATA
semverish-1.0.0.dist-info/WHEEL
semverish-1.0.0.dist-info/top_level.txt
semverish-1.0.0.dist-info/RECORD
