Metadata-Version: 2.4
Name: semverish
Version: 1.0.0
Summary: Python wrapper around Go module `github.com/rng70/versions` for parsing and sorting semver and non-semver-ish versions and constraints.
Home-page: https://github.com/rng70/versions
Author: Al Arafat Tanin
Author-email: arafat.rng70@gmail.com
License: MIT
Project-URL: Bug Tracker, https://github.com/rng70/versions/issues
Project-URL: Source, https://github.com/rng70/versions
Classifier: Development Status :: 5 - Production/Stable
Classifier: Intended Audience :: Developers
Classifier: License :: OSI Approved :: MIT License
Classifier: Programming Language :: Python :: 3
Classifier: Programming Language :: Go
Classifier: Operating System :: POSIX :: Linux
Classifier: Topic :: Software Development :: Libraries :: Python Modules
Requires-Python: >=3.8
Requires-Dist: cffi>=1.15.0
Dynamic: author
Dynamic: author-email
Dynamic: classifier
Dynamic: description
Dynamic: description-content-type
Dynamic: home-page
Dynamic: license
Dynamic: project-url
Dynamic: requires-dist
Dynamic: requires-python
Dynamic: summary
